firepyer/__init__.py
firepyer/exceptions.py
firepyer/utils.py
firepyer-0.0.7.dist-info/LICENSE
firepyer-0.0.7.dist-info/METADATA
firepyer-0.0.7.dist-info/NOTICE
firepyer-0.0.7.dist-info/WHEEL
firepyer-0.0.7.dist-info/top_level.txt
firepyer-0.0.7.dist-info/RECORD
