Metadata-Version: 2.1
Name: firepyer
Version: 0.0.7
Summary: Interacting with Cisco FTD devices via the FDM REST API in Python
Home-page: https://github.com/certanet/firepyer
Author: Marcus Cockerill
Author-email: marcus@certa.network
License: Apache License 2.0
Keywords: cisco firepower fdm ftd rest api python
Platform: UNKNOWN
Classifier: Development Status :: 1 - Planning
Classifier: Intended Audience :: Developers
Classifier: License :: OSI Approved :: Apache Software License
Classifier: Operating System :: OS Independent
Classifier: Programming Language :: Python :: 3.8
Classifier: Programming Language :: Python :: 3.9
Requires-Python: >=3.8
License-File: LICENSE
License-File: NOTICE
Requires-Dist: requests
Requires-Dist: requests-toolbelt
